mycalc/calculator.py
bymyself_yoon-0.0.1.dist-info/METADATA
bymyself_yoon-0.0.1.dist-info/WHEEL
bymyself_yoon-0.0.1.dist-info/top_level.txt
bymyself_yoon-0.0.1.dist-info/RECORD
