Metadata-Version: 2.1
Name: bymyself-yoon
Version: 0.0.1
Summary: nice calculator
Home-page: https://github.com/bymyself-yoon/calc0001
Download-URL: https://github.com/bymyself-yoon/calc0001
Author: suyun
License: UNKNOWN
Platform: UNKNOWN
Classifier: Programming Language :: Python :: 3
